py_smtper/__init__.py
py_smtper/klass.py
py_smtper/utils.py
py_smtper-1.0.0.dist-info/LICENSE
py_smtper-1.0.0.dist-info/METADATA
py_smtper-1.0.0.dist-info/WHEEL
py_smtper-1.0.0.dist-info/top_level.txt
py_smtper-1.0.0.dist-info/RECORD
