Metadata-Version: 2.1
Name: py-smtper
Version: 1.0.0
Summary: python client library for sending smtp request (emails) easily.
Home-page: https://github.com/alisharify7/py-smtper
Author: ali sharify
Author-email: alisharifyofficial@gmail.com
License: MIT
Keywords: smtp,python-email,send-email,py-smtper,py-mailer,python-smtp-email
Classifier: License :: OSI Approved :: MIT License
Classifier: Operating System :: OS Independent
Classifier: Programming Language :: Python
Classifier: Programming Language :: Python :: 3.8
Classifier: Programming Language :: Python :: 3.9
Classifier: Programming Language :: Python :: 3.10
Classifier: Programming Language :: Python :: 3.11
Classifier: Programming Language :: Python :: 3.12
Classifier: Environment :: Web Environment
Classifier: Topic :: Security
Classifier: Topic :: Internet :: WWW/HTTP
Requires-Python: >=3.8
License-File: LICENSE
